dhart/Exceptions.py
dhart/__init__.py
dhart/common_native_functions.py
dhart/native_collections.py
dhart/native_numpy_like.py
dhart/utils.py
dhart/Example Models/VisibilityTestCases.obj
dhart/Example Models/Weston_Analysis.obj
dhart/Example Models/Weston_Analysis_z-up.obj
dhart/Example Models/Weston_meshed_no-ngon.obj
dhart/Example Models/energy_blob_zup.obj
dhart/Example Models/obstacle_plane.obj
dhart/Example Models/plane.obj
dhart/Example Models/sibenik.obj
dhart/Example Models/sponza.mtl
dhart/Example Models/sponza.obj
dhart/Example Models/teapot.obj
dhart/Examples/GenerateRandomPathsExample.py
dhart/Examples/GraphGeneratorConnections.py
dhart/Examples/GraphGeneratorExample.py
dhart/Examples/GraphGeneratorPlot.py
dhart/Examples/GraphGeneratorSlope.py
dhart/Examples/GraphToCSR.py
dhart/Examples/IndoorOutdoorVisibilityGraph.py
dhart/Examples/PathPlanning.py
dhart/Examples/PathPlanningBasic.py
dhart/Examples/PathPlanningCosts.py
dhart/Examples/PathPlanningViz.py
dhart/Examples/RaytracerExample.py
dhart/Examples/SavingGraphtoJSON.py
dhart/Examples/ViewAnalysisExample.py
dhart/Examples/ViewAnalysisFromGraph.py
dhart/Examples/ViewAnalysisPlots.py
dhart/Examples/ViewAnalysisRayWrite.py
dhart/Examples/VisibilityGraphButchersDen.py
dhart/Examples/VisibilityGraphExample.py
dhart/Examples/VisibilityGraphGroups.py
dhart/Examples/VisibilityGraphPlots.py
dhart/Examples/VisibilityGraphScoreWrite.py
dhart/Examples/__init__.py
dhart/Examples/benchmarker.py
dhart/Examples/shortestpathexample.py
dhart/Examples/Rhino/RhinoDisplayUtils.py
dhart/Examples/Rhino/RhinoDisplayViewAnalysis.py
dhart/Examples/Rhino/RhinoReadGraph.py
dhart/Examples/Rhino/RhinoViewAnalysisRayDisplay.py
dhart/Examples/Rhino/read_graph_from_json.py
dhart/bin/DHARTAPI.dll
dhart/bin/embree3.dll
dhart/bin/msvcp140.dll
dhart/bin/tbb.dll
dhart/bin/vcomp140.dll
dhart/bin/vcruntime140.dll
dhart/bin/vcruntime140_1.dll
dhart/geometry/__init__.py
dhart/geometry/mesh_info.py
dhart/geometry/meshinfo_native_functions.py
dhart-0.2.8.dist-info/METADATA
dhart-0.2.8.dist-info/WHEEL
dhart-0.2.8.dist-info/top_level.txt
dhart-0.2.8.dist-info/zip-safe
dhart-0.2.8.dist-info/RECORD
