Metadata-Version: 2.1
Name: dhart
Version: 0.2.8
Summary: Design Humans Analysis RoboTics
Home-page: https://github.com/cadop/dhart
Author: 
Author-email: 
Classifier: Programming Language :: Python :: 3
Classifier: License :: OSI Approved :: GNU General Public License v3 (GPLv3)
Classifier: Operating System :: Microsoft :: Windows :: Windows 10
Requires-Python: >=3.6
Requires-Dist: numpy
Requires-Dist: scipy
Requires-Dist: matplotlib
